{
  "kind": "quant_outcomes",
  "generated_at": "2026-04-29T23:41:10+00:00",
  "evaluated_count": 6,
  "hit_count": 2,
  "hit_rate": 0.3333,
  "outcomes": [
    {
      "snapshot_id": 1552,
      "horizon_min": 60,
      "target_pct": 10.0,
      "evaluated_ts": "2026-04-29T23:41:09+00:00",
      "chain": "solana",
      "address": "JB8rMqyFmypiMqjiJ13bitubssM6aYDdq5ndUF5Wpump",
      "symbol": "BP",
      "label": "watch",
      "predicted_direction": "up",
      "entry_price": 7.785e-05,
      "current_price": 0.0002118,
      "return_pct": 172.0617,
      "is_true": true,
      "reasons": [
        "predicted_up",
        "return_172.06pct",
        "target_10.00pct",
        "label_watch",
        "pump_confirmed"
      ]
    },
    {
      "snapshot_id": 1548,
      "horizon_min": 60,
      "target_pct": 10.0,
      "evaluated_ts": "2026-04-29T23:41:09+00:00",
      "chain": "solana",
      "address": "CzuZQGdgxmjKqKkrwNr5uL4dC32aYThp1kg7S6kjpump",
      "symbol": "MCHOUSE",
      "label": "anomaly_watch",
      "predicted_direction": "up",
      "entry_price": 8.599e-06,
      "current_price": 8.481e-06,
      "return_pct": -1.3723,
      "is_true": false,
      "reasons": [
        "predicted_up",
        "return_-1.37pct",
        "target_10.00pct",
        "label_anomaly_watch",
        "not_confirmed"
      ]
    },
    {
      "snapshot_id": 1546,
      "horizon_min": 60,
      "target_pct": 10.0,
      "evaluated_ts": "2026-04-29T23:41:09+00:00",
      "chain": "solana",
      "address": "BBEsTnKaiLxmL75XEYFu72n75VtdaSxb7pTFdKsLrUxG",
      "symbol": "FTP",
      "label": "watch",
      "predicted_direction": "up",
      "entry_price": 2.716e-05,
      "current_price": 1.746e-05,
      "return_pct": -35.7143,
      "is_true": false,
      "reasons": [
        "predicted_up",
        "return_-35.71pct",
        "target_10.00pct",
        "label_watch",
        "not_confirmed"
      ]
    },
    {
      "snapshot_id": 1542,
      "horizon_min": 60,
      "target_pct": 10.0,
      "evaluated_ts": "2026-04-29T23:41:09+00:00",
      "chain": "solana",
      "address": "E8syR4zsgQG2zo9YyiyfX4ujubByR4z6qj9stjASpump",
      "symbol": "STJUDE",
      "label": "anomaly_watch",
      "predicted_direction": "up",
      "entry_price": 0.001447,
      "current_price": 0.0007952,
      "return_pct": -45.0449,
      "is_true": false,
      "reasons": [
        "predicted_up",
        "return_-45.04pct",
        "target_10.00pct",
        "label_anomaly_watch",
        "not_confirmed"
      ]
    },
    {
      "snapshot_id": 1539,
      "horizon_min": 60,
      "target_pct": 10.0,
      "evaluated_ts": "2026-04-29T23:41:10+00:00",
      "chain": "solana",
      "address": "3KHMZhpthXuiCcgfTv7vVu9PpEz64KAEURFwi6Lopump",
      "symbol": "Goblin",
      "label": "anomaly_watch",
      "predicted_direction": "down",
      "entry_price": 0.001256,
      "current_price": 0.0009989,
      "return_pct": -20.4697,
      "is_true": true,
      "reasons": [
        "predicted_down",
        "return_-20.47pct",
        "target_10.00pct",
        "label_anomaly_watch",
        "dump_confirmed"
      ]
    },
    {
      "snapshot_id": 1537,
      "horizon_min": 60,
      "target_pct": 10.0,
      "evaluated_ts": "2026-04-29T23:41:10+00:00",
      "chain": "solana",
      "address": "6AVAUKa9uxQpruHZUinFECpXEh1usRVtzQWK8N2wpump",
      "symbol": "SCAM",
      "label": "anomaly_watch",
      "predicted_direction": "down",
      "entry_price": 0.0006975,
      "current_price": 0.0007308,
      "return_pct": 4.7742,
      "is_true": false,
      "reasons": [
        "predicted_down",
        "return_4.77pct",
        "target_10.00pct",
        "label_anomaly_watch",
        "not_confirmed"
      ]
    }
  ]
}