{
  "kind": "quant_signals",
  "generated_at": "2026-04-25T09:35:38+00:00",
  "snapshot_count": 7,
  "errors": [
    "polygon:pos_0x87bdfbe98ba55104701b2f2e999982a317905637: 'NoneType' object is not iterable",
    "polygon:pos_0x1bdf71ede1a4777db1eebe7232bcda20d6fc1610: 'NoneType' object is not iterable",
    "polygon:pos_0x8f3cf7ad23cd3cadbd9735aff958023239c6a063: 'NoneType' object is not iterable",
    "polygon:pos_0x3c499c542cef5e3811e1192ce70d8cc03d5c3359: 'NoneType' object is not iterable",
    "polygon:pos_0x2791bca1f2de4661ed88a30c99a7a9449aa84174: 'NoneType' object is not iterable",
    "polygon:pos_0x708383ae0e80e75377d664e4d6344404dede119a: 'NoneType' object is not iterable",
    "polygon:pos_0x2c72d25530191ebd244eb6325e1892480b0e6e28: 'NoneType' object is not iterable",
    "polygon:pos_0x306fd3e7b169aa4ee19412323e1a5995b8c1a1f4: 'NoneType' object is not iterable",
    "polygon:pos_0x2d0f0b86280baec90b5f5e990f39a17f2be20995: 'NoneType' object is not iterable",
    "polygon:pos_0xc0bdfe1e2c63ce92fef144180e108e1652a618f2: 'NoneType' object is not iterable",
    "polygon:pos_0x582d87ddbacedfef793e35dd978f1e9fb3bda985: 'NoneType' object is not iterable",
    "polygon:pos_0xa310f955db43dd68dd340cbb5605949ae3205d05: 'NoneType' object is not iterable",
    "polygon:pos_0x94025780a1ab58868d9b2dbbb775f44b32e8e6e5: 'NoneType' object is not iterable",
    "polygon:pos_0xbfd513c0a1626e2f8ce391ceb3755a4f73135557: 'NoneType' object is not iterable",
    "polygon:pos_0xf4dd29bbc00abc73ecb43bdd548289ba7e6414f3: 'NoneType' object is not iterable"
  ],
  "filters": {
    "scan_chains": [
      "polygon",
      "optimism",
      "zksync"
    ],
    "binance_usdt_only": false,
    "binance_symbol_count": 0,
    "binance_min_liquidity_usd": 5000.0,
    "binance_source": "disabled",
    "matched_signal_count": 7
  },
  "signals": [
    {
      "snapshot_id": 404,
      "ts": "2026-04-25T09:35:32+00:00",
      "chain": "optimism",
      "address": "0x4200000000000000000000000000000000000042",
      "symbol": "OP",
      "binance_usdt_futures": false,
      "binance_symbol": "",
      "binance_base_asset": "",
      "binance_match_type": "",
      "pump_score": 2.99,
      "dump_score": 12.5,
      "anomaly_score": 23.49,
      "smart_money_score": 0.0,
      "risk_score": 50.0,
      "label": "watch",
      "reasons": [
        "risk:mintable",
        "risk:freeze_authority"
      ],
      "metrics": {
        "price": 0.1305,
        "liquidity_usd": 538079.38,
        "price_change_1h_pct": 0.83,
        "derived_price_change_pct": 0.6944444444444536,
        "volume_1h_usd": 147290.96,
        "hourly_volume_ratio": 2.4676513543313945,
        "buy_imbalance": 0.0,
        "whale_net_usd": 0.0,
        "liquidity_change_pct": 0.17380942979407357,
        "top_trader_pnl_usd": 0
      }
    },
    {
      "snapshot_id": 409,
      "ts": "2026-04-25T09:35:32+00:00",
      "chain": "optimism",
      "address": "0x94b008aa00579c1307b0ef2c499ad98a8ce58e58",
      "symbol": "WETH",
      "binance_usdt_futures": false,
      "binance_symbol": "",
      "binance_base_asset": "",
      "binance_match_type": "",
      "pump_score": 0.0,
      "dump_score": 12.56,
      "anomaly_score": 1.18,
      "smart_money_score": 0.0,
      "risk_score": 50.0,
      "label": "watch",
      "reasons": [
        "risk:mintable",
        "risk:freeze_authority"
      ],
      "metrics": {
        "price": 2318.43,
        "liquidity_usd": 440100.69,
        "price_change_1h_pct": -0.04,
        "derived_price_change_pct": -0.05819517368027846,
        "volume_1h_usd": 510.37,
        "hourly_volume_ratio": 0.1221695343558678,
        "buy_imbalance": 0.0,
        "whale_net_usd": 0.0,
        "liquidity_change_pct": -0.038240253317826,
        "top_trader_pnl_usd": 0
      }
    },
    {
      "snapshot_id": 408,
      "ts": "2026-04-25T09:35:32+00:00",
      "chain": "optimism",
      "address": "0x9560e827af36c94d2ac33a39bce1fe78631088db",
      "symbol": "VELO",
      "binance_usdt_futures": false,
      "binance_symbol": "",
      "binance_base_asset": "",
      "binance_match_type": "",
      "pump_score": 0.0,
      "dump_score": 12.5,
      "anomaly_score": 0.38,
      "smart_money_score": 0.0,
      "risk_score": 50.0,
      "label": "watch",
      "reasons": [
        "risk:mintable",
        "risk:freeze_authority"
      ],
      "metrics": {
        "price": 0.01651,
        "liquidity_usd": 647124.78,
        "price_change_1h_pct": 0.01,
        "derived_price_change_pct": 0.0,
        "volume_1h_usd": 7.32,
        "hourly_volume_ratio": 0.04027787330627967,
        "buy_imbalance": 0.0,
        "whale_net_usd": 0.0,
        "liquidity_change_pct": 0.00939783434396075,
        "top_trader_pnl_usd": 0
      }
    },
    {
      "snapshot_id": 406,
      "ts": "2026-04-25T09:35:32+00:00",
      "chain": "optimism",
      "address": "0x1e925de1c68ef83bd98ee3e130ef14a50309c01b",
      "symbol": "EXA",
      "binance_usdt_futures": false,
      "binance_symbol": "",
      "binance_base_asset": "",
      "binance_match_type": "",
      "pump_score": 0.27,
      "dump_score": 6.25,
      "anomaly_score": 10.72,
      "smart_money_score": 0.0,
      "risk_score": 25.0,
      "label": "watch",
      "reasons": [
        "risk:freeze_authority"
      ],
      "metrics": {
        "price": 0.1615,
        "liquidity_usd": 115511.04,
        "price_change_1h_pct": 0.8,
        "derived_price_change_pct": 0.685785536159612,
        "volume_1h_usd": 186.03,
        "hourly_volume_ratio": 1.0373010359720922,
        "buy_imbalance": 0.0,
        "whale_net_usd": 0.0,
        "liquidity_change_pct": 0.37142567415562644,
        "top_trader_pnl_usd": 0
      }
    },
    {
      "snapshot_id": 410,
      "ts": "2026-04-25T09:35:32+00:00",
      "chain": "optimism",
      "address": "0x0000000000000000000000000000000000000000",
      "symbol": "ETH",
      "binance_usdt_futures": false,
      "binance_symbol": "",
      "binance_base_asset": "",
      "binance_match_type": "",
      "pump_score": 0.0,
      "dump_score": 6.27,
      "anomaly_score": 0.38,
      "smart_money_score": 0.0,
      "risk_score": 25.0,
      "label": "watch",
      "reasons": [
        "risk:freeze_authority"
      ],
      "metrics": {
        "price": 2316.45,
        "liquidity_usd": 31188477.15,
        "price_change_1h_pct": -0.0017267503852796094,
        "derived_price_change_pct": -0.0017267503852796094,
        "volume_1h_usd": 1374.14,
        "hourly_volume_ratio": 0.040017470185253416,
        "buy_imbalance": 0.0,
        "whale_net_usd": 0.0,
        "liquidity_change_pct": -0.024311402375168684,
        "top_trader_pnl_usd": 0
      }
    },
    {
      "snapshot_id": 405,
      "ts": "2026-04-25T09:35:32+00:00",
      "chain": "optimism",
      "address": "0x0b2c639c533813f4aa9d7837caf62653d097ff85",
      "symbol": "USDC",
      "binance_usdt_futures": false,
      "binance_symbol": "",
      "binance_base_asset": "",
      "binance_match_type": "",
      "pump_score": 0.0,
      "dump_score": 6.25,
      "anomaly_score": 0.53,
      "smart_money_score": 0.0,
      "risk_score": 25.0,
      "label": "watch",
      "reasons": [
        "risk:freeze_authority"
      ],
      "metrics": {
        "price": 1.0017,
        "liquidity_usd": 3894569.5,
        "price_change_1h_pct": 0.15,
        "derived_price_change_pct": 0.14596496840758386,
        "volume_1h_usd": 265.63,
        "hourly_volume_ratio": 0.010494097588628517,
        "buy_imbalance": 0.0,
        "whale_net_usd": 0.0,
        "liquidity_change_pct": 0.31517334232462896,
        "top_trader_pnl_usd": 0
      }
    },
    {
      "snapshot_id": 407,
      "ts": "2026-04-25T09:35:32+00:00",
      "chain": "optimism",
      "address": "0x4200000000000000000000000000000000000006",
      "symbol": "WETH",
      "binance_usdt_futures": false,
      "binance_symbol": "",
      "binance_base_asset": "",
      "binance_match_type": "",
      "pump_score": 0.0,
      "dump_score": 6.25,
      "anomaly_score": 0.05,
      "smart_money_score": 0.0,
      "risk_score": 25.0,
      "label": "watch",
      "reasons": [
        "risk:freeze_authority"
      ],
      "metrics": {
        "price": 2315.33,
        "liquidity_usd": 122845912.18,
        "price_change_1h_pct": 0.0,
        "derived_price_change_pct": 0.0,
        "volume_1h_usd": 704.78,
        "hourly_volume_ratio": 0.0008053663416569653,
        "buy_imbalance": 0.0,
        "whale_net_usd": 0.0,
        "liquidity_change_pct": 0.06382220229661771,
        "top_trader_pnl_usd": 0
      }
    }
  ]
}